README
setup.py
bin/mnscmd
mns/__init__.py
mns/account.py
mns/mns_client.py
mns/mns_exception.py
mns/mns_http.py
mns/mns_request.py
mns/mns_tool.py
mns/mns_xml_handler.py
mns/pkg_info.py
mns/queue.py
mns.egg-info/PKG-INFO
mns.egg-info/SOURCES.txt
mns.egg-info/dependency_links.txt
mns.egg-info/top_level.txt