Metadata-Version: 1.0
Name: mns
Version: 1.0.2
Summary: Aliyun Message And Notification Service Library
Home-page: UNKNOWN
Author: Aliyun MNS
Author-email: UNKNOWN
License: MIT
Platform: UNKNOWN
